cxc_to
cxc_toolkit/__init__.py
cxc_toolkit/byte.py
cxc_toolkit/con
cxc_toolkit/hodgepodge.py
cxc_toolkit/integer.py
cxc_toolkit/patte
cxc_toolkit/patter
cxc_toolkit/tex
cxc_toolkit/concurrency/__init__.py
cxc_toolkit/concurrency/filelock.py
cxc_toolkit/concurrency/shared_value.py
cxc_toolkit/dicts/__init__.py
cxc_toolkit/dicts/check.py
cxc_toolkit/exec/__init__.py
cxc_toolkit/patterns/__init__.py
cxc_toolkit/patterns/singleton.py
cxc_toolkit/text/__init__.py
cxc_toolkit/text/string/__init__.py
cxc_toolkit/text/string/intern_conversion.py
cxc_toolkit-1.0.0.dist-info/licenses/LICENSE
tests/__init__.py
tests/t
tests/test_
tests/test_byte.py
tests/test_concu
tests/test_hodgepodge.py
tests/test_integer.py
tests/test_pa
tests/test_concurrency/__init__.py
tests/test_concurrency/test_filelock.py
tests/test_concurrency/test_shared_value.py
tests/test_exec/__init__.py
tests/test_patterns/__init__.py
tests/test_patterns/test_singleton.py
tests/test_text/__init__.py
tests/test_text/test_string.py
cxc_toolkit-1.0.0.dist-info/METADATA
cxc_toolkit-1.0.0.dist-info/WHEEL
cxc_toolkit-1.0.0.dist-info/top_level.txt
cxc_toolkit-1.0.0.dist-info/RECORD
