Metadata-Version: 2.4
Name: cxc-toolkit
Version: 1.0.0
Summary: Toolbox contains a lot of utility functions
Home-page: https://github.com/XiaochenCui/cxc-toolkit
Author: Xiaochen Cui
Author-email: jcnlcxc.new@gmail.com
License: GPLv3
Keywords: toolkit
Classifier: Development Status :: 1 - Planning
Classifier: Intended Audience :: Developers
Classifier: Topic :: Software Development :: Libraries :: Python Modules
Classifier: License :: OSI Approved :: GNU General Public License v3 (GPLv3)
Classifier: Programming Language :: Python :: 3
Classifier: Programming Language :: Python :: 3.6
Classifier: Programming Language :: Python :: 3 :: Only
License-File: LICENSE
Requires-Dist: psutil
Dynamic: author
Dynamic: author-email
Dynamic: classifier
Dynamic: description
Dynamic: home-page
Dynamic: keywords
Dynamic: license
Dynamic: license-file
Dynamic: requires-dist
Dynamic: summary
